tox_pin_deps/__init__.py
tox_pin_deps/common.py
tox_pin_deps/compile.py
tox_pin_deps/loader.py
tox_pin_deps/plugin.py
tox_pin_deps/plugin4.py
tox_pin_deps/py.typed
tox_pin_deps-0.2.2.dist-info/LICENSE
tox_pin_deps-0.2.2.dist-info/METADATA
tox_pin_deps-0.2.2.dist-info/WHEEL
tox_pin_deps-0.2.2.dist-info/entry_points.txt
tox_pin_deps-0.2.2.dist-info/top_level.txt
tox_pin_deps-0.2.2.dist-info/RECORD
