Metadata-Version: 2.1
Name: tox-pin-deps
Version: 0.2.2
Summary: A tox plugin for pinning dependencies.
Author-email: Masen Furer <m_github@0x26.net>
License: MIT License
Project-URL: Homepage, https://github.com/masenf/tox-pin-deps
Platform: unix
Platform: linux
Platform: osx
Platform: cygwin
Platform: win32
Classifier: Development Status :: 4 - Beta
Classifier: Intended Audience :: Developers
Classifier: License :: OSI Approved :: MIT License
Classifier: Operating System :: POSIX
Classifier: Operating System :: Microsoft :: Windows
Classifier: Operating System :: MacOS :: MacOS X
Classifier: Topic :: Software Development :: Testing
Classifier: Topic :: Software Development :: Libraries
Classifier: Topic :: Utilities
Classifier: Programming Language :: Python
Requires-Python: >=3.7
License-File: LICENSE
